clkUnit/diviseurClkRX.vhd
library IEEE;
use IEEE.std_logic_1164.all;

entity diviseurClkRX is
  -- facteur : ratio entre la fréquence de l'horloge origine et celle
  --           de l'horloge générée
  --  ex : 100 MHz -> 1Hz : 100 000 000
  --  ex : 100 MHz -> 1kHz : 100 000
  port (
    clk, reset : in  std_logic;
    nclk       : out std_logic);
end diviseurClkRX;

architecture arch_divClk of diviseurClkRX is

  signal top : std_logic := '0';
  constant facteur : natural := 10;
  
begin  

  div : process (clk, reset)
    variable cpt : integer range 0 to facteur-1 := 0;
  begin 
    if reset = '0' then
      nclk <= '0';
      cpt := 0;
    elsif rising_edge(clk) then
      if(cpt = facteur - 1) then
        cpt := 0;
      else
        cpt := cpt + 1;
      end if;
      if cpt = 0 then
        nclk <= '1';
      else
        nclk <= '0';
      end if;
    end if;
  end process;

end arch_divClk;

clkUnit/diviseurClkTX.vhd
library IEEE;
use IEEE.std_logic_1164.all;

entity diviseurClkTX is
  -- facteur : ratio entre la fréquence de l'horloge origine et celle
  --           de l'horloge générée
  --  ex : 100 MHz -> 1Hz : 100 000 000
  --  ex : 100 MHz -> 1kHz : 100 000
  port (
    clk, reset : in  std_logic;
    nclk       : out std_logic);
end diviseurClkTX;

architecture arch_divClk of diviseurClkTX is

  signal top : std_logic := '0';
  constant facteur : natural := 160;
  
begin  

  div : process (clk, reset)
    variable cpt : integer range 0 to facteur-1 := 0;
  begin 
    if reset = '0' then
      nclk <= '0';
      cpt := 0;
    elsif rising_edge(clk) then
      if(cpt = facteur - 1) then
        cpt := 0;
      else
        cpt := cpt + 1;
      end if;
      if cpt = 0 then
        nclk <= '1';
      else
        nclk <= '0';
      end if;
    end if;
  end process;

end arch_divClk;

clkUnit/clkUnit.vhd
library IEEE;
use IEEE.std_logic_1164.all;

entity clkUnit is
 port (
        clk, reset : in  std_logic;
        enableTX   : out std_logic;
        enableRX   : out std_logic
      );
end clkUnit;

architecture behavorial of clkUnit is

  COMPONENT diviseurClkTX is 
    PORT (
         clk, reset : in  std_logic;
    nclk       : out std_logic);

  END COMPONENT;

  COMPONENT diviseurClkRX is 
    PORT (
         clk, reset : in  std_logic;
    nclk       : out std_logic);

  END COMPONENT;

begin

  -- affectation des sorties pour que la simulation et la génération du bitstream aillent jusqu'au bout
  U1 : diviseurClkTX Port map (
    clk => clk ,
    reset => reset ,
    nclk => enableTX
  );

  U2 : diviseurClkRX Port map (
    clk => clk ,
    reset => reset ,
    nclk => enableRX
  );


end behavorial;

TxUnit/TxUnit.vhd
library IEEE;
use IEEE.std_logic_1164.all;

entity TxUnit is
  port (
    clk, reset : in std_logic;
    enable     : in std_logic;
    ld         : in std_logic;
    txd        : out std_logic;
    regE       : out std_logic;
    bufE       : out std_logic;
    data       : in std_logic_vector(7 downto 0));
end TxUnit;

architecture behavorial of TxUnit is

  -- États de l'automate
  signal etat : std_logic_vector(2 downto 0) := "000";

  -- Tampon de transmission
  signal Buffer_T : std_logic_vector(7 downto 0);

  -- Registre d’émission
  signal Register_T : std_logic_vector(7 downto 0);

begin

  unite_proc: process(clk, reset)

    -- Compteur des bits transmis
    variable cpt : natural := 7;

  begin

    -- Réinitialisation de l'unité
    if reset = '0' then

      etat      <= "000";     -- État initial
      Buffer_T  <= (others => '0');
      txd       <= '1';       -- Ligne au repos
      regE      <= '1';       -- Registre libre
      bufE      <= '1';       -- Tampon libre

    elsif rising_edge(clk) then

      -- Automate principal
      case etat is

        -- État initial
        when "000" =>

          -- Attente d’une demande d’émission
          if ld = '1' then
            Buffer_T <= data;   -- Chargement des données
            bufE     <= '0';
            etat     <= "001";
          end if;

        -- Transfert du tampon vers le registre
        when "001" =>
          Register_T <= Buffer_T;
          bufE       <= '1';
          regE       <= '0';
          etat       <= "010";

        -- Envoi du bit de start
        when "010" =>

          -- Début de trame si autorisé
          if enable = '1' then
            txd <= '0';         -- Bit de start
            cpt := 7;
            etat <= "011";

            -- Charger une nouvelle donnée si le tampon est libre
            if ld = '1' and bufE = '1' then
              Buffer_T <= data;
              bufE <= '0';
            end if;

          end if;

        -- Transmission des bits de données
        when "011" =>

          if (cpt > 0 and enable = '1') then
            txd <= Register_T(cpt);
            cpt := cpt - 1;

          elsif (cpt = 0 and enable = '1') then
            txd  <= Register_T(0);
            etat <= "100";  -- Passage au bit de stop
          end if;

          -- Charger une donnée si le tampon est libre
          if ld = '1' and bufE = '1' then
            Buffer_T <= data;
            bufE <= '0';
          end if;

        -- Fin de transmission de la trame
        when "100" =>

          -- S’il y a une nouvelle trame en attente
          if bufE = '0' and enable = '1' then
            txd  <= '1';      -- Bit de stop
            regE <= '1';
            etat <= "001";

          -- Sinon, retour à l’état initial
          elsif bufE = '1' and enable = '1' then
            txd  <= '1';
            regE <= '1';
            etat <= "000";
          end if;

          -- Charger une nouvelle donnée si le tampon est libre
          if ld = '1' and bufE = '1' then
            Buffer_T <= data;
            bufE <= '0';
          end if;

        when others =>
          null;

      end case;

    end if;

  end process;

end behavorial;

TxUnit/testTxUnit.vhd
--------------------------------------------------------------------------------
-- Company: 
-- Engineer:
--
-- Create Date:   12:09:49 10/31/2018
-- Design Name:   
-- Module Name:   testTxUnit.vhd
-- Project Name:  uart
-- Target Device:  
-- Tool versions:  
-- Description:   
-- 
-- VHDL Test Bench Created by ISE for module: TxUnit
-- 
-- Dependencies:
-- 
-- Revision:
-- Revision 0.01 - File Created
-- Additional Comments:
--
-- Notes: 
-- This testbench has been automatically generated using types std_logic and
-- std_logic_vector for the ports of the unit under test.  Xilinx recommends
-- that these types always be used for the top-level I/O of a design in order
-- to guarantee that the testbench will bind correctly to the post-implementation 
-- simulation model.
--------------------------------------------------------------------------------
LIBRARY ieee;
USE ieee.std_logic_1164.ALL;
 
-- Uncomment the following library declaration if using
-- arithmetic functions with Signed or Unsigned values
--USE ieee.numeric_std.ALL;
 
ENTITY testTxUnit IS
END testTxUnit;
 
ARCHITECTURE behavior OF testTxUnit IS 
 
    -- Component Declaration for the Unit Under Test (UUT)
 
    COMPONENT TxUnit
    PORT(
         clk : IN  std_logic;
         reset : IN  std_logic;
         enable : IN  std_logic;
         ld : IN  std_logic;
         txd : OUT  std_logic;
         regE : OUT  std_logic;
         bufE : OUT  std_logic;
         data : IN  std_logic_vector(7 downto 0)
        );
    END COMPONENT;
   
    COMPONENT clkUnit
    PORT(
         clk : IN  std_logic;
         reset : IN  std_logic;
         enableTX : OUT  std_logic;
         enableRX : OUT  std_logic
        );
    END COMPONENT;	

   signal clk : std_logic := '0';
   signal reset : std_logic := '0';
   signal enableTx : std_logic := '0';
   signal enableRx : std_logic := '0';
   signal ld : std_logic := '0';
   signal data : std_logic_vector(7 downto 0) := (others => '0');

   signal txd : std_logic;
   signal regE : std_logic;
   signal bufE : std_logic;

   -- Clock period definitions
   constant clk_period : time := 10 ns;
 
BEGIN
 
	-- Instantiate the Unit Under Test
   uut0: TxUnit PORT MAP (
          clk => clk,
          reset => reset,
          enable => enableTX,
          ld => ld,
          txd => txd,
          regE => regE,
          bufE => bufE,
          data => data
        );

   -- Instantiate the clkUnit
   clkUnit1: clkUnit PORT MAP (
          clk => clk,
          reset => reset,
          enableTX => enableTX,
          enableRX => enableRX
        );
		  
   -- Clock process definitions
   clk_process :process
   begin
     clk <= '0';
     wait for clk_period/2;
     clk <= '1';
     wait for clk_period/2;
   end process;
 
 
   -- Stimulus process
   stim_proc: process
   begin		
     -- maintien du reset durant 100 ns.
     wait for 100 ns;	
     reset <= '1';

     wait for 200 ns;

     -- l'émetteur est dispo ?
     if not (regE='1' and bufE='1') then
       wait until regE='1' and bufE='1';
     end if;

     -- si oui, on charge la donnée
     wait for clk_period;
     -- émission du caractère 0x55
     data <= "01010101";
     ld <= '1';

     -- on attend de voir que l'ordre d'émission
     -- a été bien pris en compte avant de rabaisser
     -- le signal ld
     if not (regE='1' and bufE='0') then
       wait until regE='1' and bufE='0';
     end if;
     wait for clk_period;
     ld <= '0';
     
     -- compléter avec des tests qui montrent que la prise en compte de la demande d'émission
     -- d'un autre caractère se fait lorsqu'on émet un caractère et ceci quelque soit
     -- l'étape d'émission

     wait until bufE = '1';
     wait for 5000 us;
     data <= "10011000";
     ld <= '1';

     
     wait for clk_period;
     ld <= '0';

     wait;
   end process;

END;

TxUnit/output.vcd
$date
  Sun Dec  7 22:48:28 2025
$end
$version
  GHDL v0
$end
$timescale
  1 fs
$end
$scope module standard $end
$upscope $end
$scope module textio $end
$upscope $end
$scope module std_logic_1164 $end
$upscope $end
$scope module testtxunit $end
$var reg 1 ! clk $end
$var reg 1 " reset $end
$var reg 1 # enabletx $end
$var reg 1 $ enablerx $end
$var reg 1 % ld $end
$var reg 8 & data[7:0] $end
$var reg 1 ' txd $end
$var reg 1 ( rege $end
$var reg 1 ) bufe $end
$scope module uut0 $end
$var reg 1 * clk $end
$var reg 1 + reset $end
$var reg 1 , enable $end
$var reg 1 - ld $end
$var reg 1 . txd $end
$var reg 1 / rege $end
$var reg 1 0 bufe $end
$var reg 8 1 data[7:0] $end
$var reg 3 2 etat[2:0] $end
$var reg 8 3 buffer_t[7:0] $end
$var reg 8 4 register_t[7:0] $end
$upscope $end
$scope module clkunit1 $end
$var reg 1 5 clk $end
$var reg 1 6 reset $end
$var reg 1 7 enabletx $end
$var reg 1 8 enablerx $end
$scope module u1 $end
$var reg 1 9 clk $end
$var reg 1 : reset $end
$var reg 1 ; nclk $end
$var reg 1 < top $end
$upscope $end
$scope module u2 $end
$var reg 1 = clk $end
$var reg 1 > reset $end
$var reg 1 ? nclk $end
$var reg 1 @ top $end
$upscope $end
$upscope $end
$upscope $end
$enddefinitions $end
#0
0!
0"
0#
0$
0%
b00000000 &
1'
1(
1)
0*
0+
0,
0-
1.
1/
10
b00000000 1
b000 2
b00000000 3
bUUUUUUUU 4
05
06
07
08
09
0:
0;
0<
0=
0>
0?
0@
#5000000
1!
1*
15
19
1=
#10000000
0!
0*
05
09
0=
#15000000
1!
1*
15
19
1=
#20000000
0!
0*
05
09
0=
#25000000
1!
1*
15
19
1=
#30000000
0!
0*
05
09
0=
#35000000
1!
1*
15
19
1=
#40000000
0!
0*
05
09
0=
#45000000
1!
1*
15
19
1=
#50000000
0!
0*
05
09
0=
#55000000
1!
1*
15
19
1=
#60000000
0!
0*
05
09
0=
#65000000
1!
1*
15
19
1=
#70000000
0!
0*
05
09
0=
#75000000
1!
1*
15
19
1=
#80000000
0!
0*
05
09
0=
#85000000
1!
1*
15
19
1=
#90000000
0!
0*
05
09
0=
#95000000
1!
1*
15
19
1=
#100000000
0!
1"
0*
1+
05
16
09
1:
0=
1>
#105000000
1!
1*
15
19
1=
#110000000
0!
0*
05
09
0=
#115000000
1!
1*
15
19
1=
#120000000
0!
0*
05
09
0=
#125000000
1!
1*
15
19
1=
#130000000
0!
0*
05
09
0=
#135000000
1!
1*
15
19
1=
#140000000
0!
0*
05
09
0=
#145000000
1!
1*
15
19
1=
#150000000
0!
0*
05
09
0=
#155000000
1!
1*
15
19
1=
#160000000
0!
0*
05
09
0=
#165000000
1!
1*
15
19
1=
#170000000
0!
0*
05
09
0=
#175000000
1!
1*
15
19
1=
#180000000
0!
0*
05
09
0=
#185000000
1!
1*
15
19
1=
#190000000
0!
0*
05
09
0=
#195000000
1!
1$
1*
15
18
19
1=
1?
#200000000
0!
0*
05
09
0=
#205000000
1!
0$
1*
15
08
19
1=
0?
#210000000
0!
0*
05
09
0=
#215000000
1!
1*
15
19
1=
#220000000
0!
0*
05
09
0=
#225000000
1!
1*
15
19
1=
#230000000
0!
0*
05
09
0=
#235000000
1!
1*
15
19
1=
#240000000
0!
0*
05
09
0=
#245000000
1!
1*
15
19
1=
#250000000
0!
0*
05
09
0=
#255000000
1!
1*
15
19
1=
#260000000
0!
0*
05
09
0=
#265000000
1!
1*
15
19
1=
#270000000
0!
0*
05
09
0=
#275000000
1!
1*
15
19
1=
#280000000
0!
0*
05
09
0=
#285000000
1!
1*
15
19
1=
#290000000
0!
0*
05
09
0=
#295000000
1!
1$
1*
15
18
19
1=
1?
#300000000
0!
0*
05
09
0=
#305000000
1!
0$
1*
15
08
19
1=
0?
#310000000
0!
1%
b01010101 &
0*
1-
b01010101 1
05
09
0=
#315000000
1!
0)
1*
00
b001 2
b01010101 3
15
19
1=
#320000000
0!
0*
05
09
0=
#325000000
1!
0%
0(
1)
1*
0-
0/
10
b010 2
b01010101 4
15
19
1=
#330000000
0!
0*
05
09
0=
#335000000
1!
1*
15
19
1=
#340000000
0!
0*
05
09
0=
#345000000
1!
1*
15
19
1=
#350000000
0!
0*
05
09
0=
#355000000
1!
1*
15
19
1=
#360000000
0!
0*
05
09
0=
#365000000
1!
1*
15
19
1=
#370000000
0!
0*
05
09
0=
#375000000
1!
1*
15
19
1=
#380000000
0!
0*
05
09
0=
#385000000
1!
1*
15
19
1=
#390000000
0!
0*
05
09
0=
#395000000
1!
1$
1*
15
18
19
1=
1?
#400000000
0!
0*
05
09
0=
#405000000
1!
0$
1*
15
08
19
1=
0?
#410000000
0!
0*
05
09
0=
#415000000
1!
1*
15
19
1=
#420000000
0!
0*
05
09
0=
#425000000
1!
1*
15
19
1=
#430000000
0!
0*
05
09
0=
#435000000
1!
1*
15
19
1=
#440000000
0!
0*
05
09
0=
#445000000
1!
1*
15
19
1=
#450000000
0!
0*
05
09
0=
#455000000
1!
1*
15
19
1=
#460000000
0!
0*
05
09
0=
#465000000
1!
1*
15
19
1=
#470000000
0!
0*
05
09
0=
#475000000
1!
1*
15
19
1=
#480000000
0!
0*
05
09
0=
#485000000
1!
1*
15
19
1=
#490000000
0!
0*
05
09
0=
#495000000
1!
1$
1*
15
18
19
1=
1?
#500000000
0!
0*
05
09
0=
#505000000
1!
0$
1*
15
08
19
1=
0?
#510000000
0!
0*
05
09
0=
#515000000
1!
1*
15
19
1=
#520000000
0!
0*
05
09
0=
#525000000
1!
1*
15
19
1=
#530000000
0!
0*
05
09
0=
#535000000
1!
1*
15
19
1=
#540000000
0!
0*
05
09
0=
#545000000
1!
1*
15
19
1=
#550000000
0!
0*
05
09
0=
#555000000
1!
1*
15
19
1=
#560000000
0!
0*
05
09
0=
#565000000
1!
1*
15
19
1=
#570000000
0!
0*
05
09
0=
#575000000
1!
1*
15
19
1=
#580000000
0!
0*
05
09
0=
#585000000
1!
1*
15
19
1=
#590000000
0!
0*
05
09
0=
#595000000
1!
1$
1*
15
18
19
1=
1?
#600000000
0!
0*
05
09
0=
#605000000
1!
0$
1*
15
08
19
1=
0?
#610000000
0!
0*
05
09
0=
#615000000
1!
1*
15
19
1=
#620000000
0!
0*
05
09
0=
#625000000
1!
1*
15
19
1=
#630000000
0!
0*
05
09
0=
#635000000
1!
1*
15
19
1=
#640000000
0!
0*
05
09
0=
#645000000
1!
1*
15
19
1=
#650000000
0!
0*
05
09
0=
#655000000
1!
1*
15
19
1=
#660000000
0!
0*
05
09
0=
#665000000
1!
1*
15
19
1=
#670000000
0!
0*
05
09
0=
#675000000
1!
1*
15
19
1=
#680000000
0!
0*
05
09
0=
#685000000
1!
1*
15
19
1=
#690000000
0!
0*
05
09
0=
#695000000
1!
1$
1*
15
18
19
1=
1?
#700000000
0!
0*
05
09
0=
#705000000
1!
0$
1*
15
08
19
1=
0?
#710000000
0!
0*
05
09
0=
#715000000
1!
1*
15
19
1=
#720000000
0!
0*
05
09
0=
#725000000
1!
1*
15
19
1=
#730000000
0!
0*
05
09
0=
#735000000
1!
1*
15
19
1=
#740000000
0!
0*
05
09
0=
#745000000
1!
1*
15
19
1=
#750000000
0!
0*
05
09
0=
#755000000
1!
1*
15
19
1=
#760000000
0!
0*
05
09
0=
#765000000
1!
1*
15
19
1=
#770000000
0!
0*
05
09
0=
#775000000
1!
1*
15
19
1=
#780000000
0!
0*
05
09
0=
#785000000
1!
1*
15
19
1=
#790000000
0!
0*
05
09
0=
#795000000
1!
1$
1*
15
18
19
1=
1?
#800000000
0!
0*
05
09
0=
#805000000
1!
0$
1*
15
08
19
1=
0?
#810000000
0!
0*
05
09
0=
#815000000
1!
1*
15
19
1=
#820000000
0!
0*
05
09
0=
#825000000
1!
1*
15
19
1=
#830000000
0!
0*
05
09
0=
#835000000
1!
1*
15
19
1=
#840000000
0!
0*
05
09
0=
#845000000
1!
1*
15
19
1=
#850000000
0!
0*
05
09
0=
#855000000
1!
1*
15
19
1=
#860000000
0!
0*
05
09
0=
#865000000
1!
1*
15
19
1=
#870000000
0!
0*
05
09
0=
#875000000
1!
1*
15
19
1=
#880000000
0!
0*
05
09
0=
#885000000
1!
1*
15
19
1=
#890000000
0!
0*
05
09
0=
#895000000
1!
1$
1*
15
18
19
1=
1?
#900000000
0!
0*
05
09
0=
#905000000
1!
0$
1*
15
08
19
1=
0?
#910000000
0!
0*
05
09
0=
#915000000
1!
1*
15
19
1=
#920000000
0!
0*
05
09
0=
#925000000
1!
1*
15
19
1=
#930000000
0!
0*
05
09
0=
#935000000
1!
1*
15
19
1=
#940000000
0!
0*
05
09
0=
#945000000
1!
1*
15
19
1=
#950000000
0!
0*
05
09
0=
#955000000
1!
1*
15
19
1=
#960000000
0!
0*
05
09
0=
#965000000
1!
1*
15
19
1=
#970000000
0!
0*
05
09
0=
#975000000
1!
1*
15
19
1=
#980000000
0!
0*
05
09
0=
#985000000
1!
1*
15
19
1=
#990000000
0!
0*
05
09
0=
#995000000
1!
1$
1*
15
18
19
1=
1?
#1000000000
0!
0*
05
09
0=
#1005000000
1!
0$
1*
15
08
19
1=
0?
#1010000000
0!
0*
05
09
0=
#1015000000
1!
1*
15
19
1=
#1020000000
0!
0*
05
09
0=
#1025000000
1!
1*
15
19
1=
#1030000000
0!
0*
05
09
0=
#1035000000
1!
1*
15
19
1=
#1040000000
0!
0*
05
09
0=
#1045000000
1!
1*
15
19
1=
#1050000000
0!
0*
05
09
0=
#1055000000
1!
1*
15
19
1=
#1060000000
0!
0*
05
09
0=
#1065000000
1!
1*
15
19
1=
#1070000000
0!
0*
05
09
0=
#1075000000
1!
1*
15
19
1=
#1080000000
0!
0*
05
09
0=
#1085000000
1!
1*
15
19
1=
#1090000000
0!
0*
05
09
0=
#1095000000
1!
1$
1*
15
18
19
1=
1?
#1100000000
0!
0*
05
09
0=
#1105000000
1!
0$
1*
15
08
19
1=
0?
#1110000000
0!
0*
05
09
0=
#1115000000
1!
1*
15
19
1=
#1120000000
0!
0*
05
09
0=
#1125000000
1!
1*
15
19
1=
#1130000000
0!
0*
05
09
0=
#1135000000
1!
1*
15
19
1=
#1140000000
0!
0*
05
09
0=
#1145000000
1!
1*
15
19
1=
#1150000000
0!
0*
05
09
0=
#1155000000
1!
1*
15
19
1=
#1160000000
0!
0*
05
09
0=
#1165000000
1!
1*
15
19
1=
#1170000000
0!
0*
05
09
0=
#1175000000
1!
1*
15
19
1=
#1180000000
0!
0*
05
09
0=
#1185000000
1!
1*
15
19
1=
#1190000000
0!
0*
05
09
0=
#1195000000
1!
1$
1*
15
18
19
1=
1?
#1200000000
0!
0*
05
09
0=
#1205000000
1!
0$
1*
15
08
19
1=
0?
#1210000000
0!
0*
05
09
0=
#1215000000
1!
1*
15
19
1=
#1220000000
0!
0*
05
09
0=
#1225000000
1!
1*
15
19
1=
#1230000000
0!
0*
05
09
0=
#1235000000
1!
1*
15
19
1=
#1240000000
0!
0*
05
09
0=
#1245000000
1!
1*
15
19
1=
#1250000000
0!
0*
05
09
0=
#1255000000
1!
1*
15
19
1=
#1260000000
0!
0*
05
09
0=
#1265000000
1!
1*
15
19
1=
#1270000000
0!
0*
05
09
0=
#1275000000
1!
1*
15
19
1=
#1280000000
0!
0*
05
09
0=
#1285000000
1!
1*
15
19
1=
#1290000000
0!
0*
05
09
0=
#1295000000
1!
1$
1*
15
18
19
1=
1?
#1300000000
0!
0*
05
09
0=
#1305000000
1!
0$
1*
15
08
19
1=
0?
#1310000000
0!
0*
05
09
0=
#1315000000
1!
1*
15
19
1=
#1320000000
0!
0*
05
09
0=
#1325000000
1!
1*
15
19
1=
#1330000000
0!
0*
05
09
0=
#1335000000
1!
1*
15
19
1=
#1340000000
0!
0*
05
09
0=
#1345000000
1!
1*
15
19
1=
#1350000000
0!
0*
05
09
0=
#1355000000
1!
1*
15
19
1=
#1360000000
0!
0*
05
09
0=
#1365000000
1!
1*
15
19
1=
#1370000000
0!
0*
05
09
0=
#1375000000
1!
1*
15
19
1=
#1380000000
0!
0*
05
09
0=
#1385000000
1!
1*
15
19
1=
#1390000000
0!
0*
05
09
0=
#1395000000
1!
1$
1*
15
18
19
1=
1?
#1400000000
0!
0*
05
09
0=
#1405000000
1!
0$
1*
15
08
19
1=
0?
#1410000000
0!
0*
05
09
0=
#1415000000
1!
1*
15
19
1=
#1420000000
0!
0*
05
09
0=
#1425000000
1!
1*
15
19
1=
#1430000000
0!
0*
05
09
0=
#1435000000
1!
1*
15
19
1=
#1440000000
0!
0*
05
09
0=
#1445000000
1!
1*
15
19
1=
#1450000000
0!
0*
05
09
0=
#1455000000
1!
1*
15
19
1=
#1460000000
0!
0*
05
09
0=
#1465000000
1!
1*
15
19
1=
#1470000000
0!
0*
05
09
0=
#1475000000
1!
1*
15
19
1=
#1480000000
0!
0*
05
09
0=
#1485000000
1!
1*
15
19
1=
#1490000000
0!
0*
05
09
0=
#1495000000
1!
1$
1*
15
18
19
1=
1?
#1500000000
0!
0*
05
09
0=
#1505000000
1!
0$
1*
15
08
19
1=
0?
#1510000000
0!
0*
05
09
0=
#1515000000
1!
1*
15
19
1=
#1520000000
0!
0*
05
09
0=
#1525000000
1!
1*
15
19
1=
#1530000000
0!
0*
05
09
0=
#1535000000
1!
1*
15
19
1=
#1540000000
0!
0*
05
09
0=
#1545000000
1!
1*
15
19
1=
#1550000000
0!
0*
05
09
0=
#1555000000
1!
1*
15
19
1=
#1560000000
0!
0*
05
09
0=
#1565000000
1!
1*
15
19
1=
#1570000000
0!
0*
05
09
0=
#1575000000
1!
1*
15
19
1=
#1580000000
0!
0*
05
09
0=
#1585000000
1!
1*
15
19
1=
#1590000000
0!
0*
05
09
0=
#1595000000
1!
1$
1*
15
18
19
1=
1?
#1600000000
0!
0*
05
09
0=
#1605000000
1!
0$
1*
15
08
19
1=
0?
#1610000000
0!
0*
05
09
0=
#1615000000
1!
1*
15
19
1=
#1620000000
0!
0*
05
09
0=
#1625000000
1!
1*
15
19
1=
#1630000000
0!
0*
05
09
0=
#1635000000
1!
1*
15
19
1=
#1640000000
0!
0*
05
09
0=
#1645000000
1!
1*
15
19
1=
#1650000000
0!
0*
05
09
0=
#1655000000
1!
1*
15
19
1=
#1660000000
0!
0*
05
09
0=
#1665000000
1!
1*
15
19
1=
#1670000000
0!
0*
05
09
0=
#1675000000
1!
1*
15
19
1=
#1680000000
0!
0*
05
09
0=
#1685000000
1!
1*
15
19
1=
#1690000000
0!
0*
05
09
0=
#1695000000
1!
1#
1$
1*
1,
15
17
18
19
1;
1=
1?
#1700000000
0!
0*
05
09
0=
#1705000000
1!
0#
0$
0'
1*
0,
0.
b011 2
15
07
08
19
0;
1=
0?
#1710000000
0!
0*
05
09
0=
#1715000000
1!
1*
15
19
1=
#1720000000
0!
0*
05
09
0=
#1725000000
1!
1*
15
19
1=
#1730000000
0!
0*
05
09
0=
#1735000000
1!
1*
15
19
1=
#1740000000
0!
0*
05
09
0=
#1745000000
1!
1*
15
19
1=
#1750000000
0!
0*
05
09
0=
#1755000000
1!
1*
15
19
1=
#1760000000
0!
0*
05
09
0=
#1765000000
1!
1*
15
19
1=
#1770000000
0!
0*
05
09
0=
#1775000000
1!
1*
15
19
1=
#1780000000
0!
0*
05
09
0=
#1785000000
1!
1*
15
19
1=
#1790000000
0!
0*
05
09
0=
#1795000000
1!
1$
1*
15
18
19
1=
1?
#1800000000
0!
0*
05
09
0=
#1805000000
1!
0$
1*
15
08
19
1=
0?
#1810000000
0!
0*
05
09
0=
#1815000000
1!
1*
15
19
1=
#1820000000
0!
0*
05
09
0=
#1825000000
1!
1*
15
19
1=
#1830000000
0!
0*
05
09
0=
#1835000000
1!
1*
15
19
1=
#1840000000
0!
0*
05
09
0=
#1845000000
1!
1*
15
19
1=
#1850000000
0!
0*
05
09
0=
#1855000000
1!
1*
15
19
1=
#1860000000
0!
0*
05
09
0=
#1865000000
1!
1*
15
19
1=
#1870000000
0!
0*
05
09
0=
#1875000000
1!
1*
15
19
1=
#1880000000
0!
0*
05
09
0=
#1885000000
1!
1*
15
19
1=
#1890000000
0!
0*
05
09
0=
#1895000000
1!
1$
1*
15
18
19
1=
1?
#1900000000
0!
0*
05
09
0=
#1905000000
1!
0$
1%
b10101010 &
0)
1*
1-
00
b10101010 1
b10101010 3
15
08
19
1=
0?
#1910000000
0!
0*
05
09
0=
#1915000000
1!
0%
1*
0-
15
19
1=
#1920000000
0!
0*
05
09
0=
#1925000000
1!
1*
15
19
1=
#1930000000
0!
0*
05
09
0=
#1935000000
1!
1*
15
19
1=
#1940000000
0!
0*
05
09
0=
#1945000000
1!
1*
15
19
1=
#1950000000
0!
0*
05
09
0=
#1955000000
1!
1*
15
19
1=
#1960000000
0!
0*
05
09
0=
#1965000000
1!
1*
15
19
1=
#1970000000
0!
0*
05
09
0=
#1975000000
1!
1*
15
19
1=
#1980000000
0!
0*
05
09
0=
#1985000000
1!
1*
15
19
1=
#1990000000
0!
0*
05
09
0=
#1995000000
1!
1$
1*
15
18
19
1=
1?
#2000000000
0!
0*
05
09
0=
#2005000000
1!
0$
1*
15
08
19
1=
0?
#2010000000
0!
0*
05
09
0=
#2015000000
1!
1*
15
19
1=
#2020000000
0!
0*
05
09
0=
#2025000000
1!
1*
15
19
1=
#2030000000
0!
0*
05
09
0=
#2035000000
1!
1*
15
19
1=
#2040000000
0!
0*
05
09
0=
#2045000000
1!
1*
15
19
1=
#2050000000
0!
0*
05
09
0=
#2055000000
1!
1*
15
19
1=
#2060000000
0!
0*
05
09
0=
#2065000000
1!
1*
15
19
1=
#2070000000
0!
0*
05
09
0=
#2075000000
1!
1*
15
19
1=
#2080000000
0!
0*
05
09
0=
#2085000000
1!
1*
15
19
1=
#2090000000
0!
0*
05
09
0=
#2095000000
1!
1$
1*
15
18
19
1=
1?
#2100000000
0!
0*
05
09
0=
#2105000000
1!
0$
1*
15
08
19
1=
0?
#2110000000
0!
0*
05
09
0=
#2115000000
1!
1*
15
19
1=
#2120000000
0!
0*
05
09
0=
#2125000000
1!
1*
15
19
1=
#2130000000
0!
0*
05
09
0=
#2135000000
1!
1*
15
19
1=
#2140000000
0!
0*
05
09
0=
#2145000000
1!
1*
15
19
1=
#2150000000
0!
0*
05
09
0=
#2155000000
1!
1*
15
19
1=
#2160000000
0!
0*
05
09
0=
#2165000000
1!
1*
15
19
1=
#2170000000
0!
0*
05
09
0=
#2175000000
1!
1*
15
19
1=
#2180000000
0!
0*
05
09
0=
#2185000000
1!
1*
15
19
1=
#2190000000
0!
0*
05
09
0=
#2195000000
1!
1$
1*
15
18
19
1=
1?
#2200000000
0!
0*
05
09
0=
#2205000000
1!
0$
1*
15
08
19
1=
0?
#2210000000
0!
0*
05
09
0=
#2215000000
1!
1*
15
19
1=
#2220000000
0!
0*
05
09
0=
#2225000000
1!
1*
15
19
1=
#2230000000
0!
0*
05
09
0=
#2235000000
1!
1*
15
19
1=
#2240000000
0!
0*
05
09
0=
#2245000000
1!
1*
15
19
1=
#2250000000
0!
0*
05
09
0=
#2255000000
1!
1*
15
19
1=
#2260000000
0!
0*
05
09
0=
#2265000000
1!
1*
15
19
1=
#2270000000
0!
0*
05
09
0=
#2275000000
1!
1*
15
19
1=
#2280000000
0!
0*
05
09
0=
#2285000000
1!
1*
15
19
1=
#2290000000
0!
0*
05
09
0=
#2295000000
1!
1$
1*
15
18
19
1=
1?
#2300000000
0!
0*
05
09
0=
#2305000000
1!
0$
1*
15
08
19
1=
0?
#2310000000
0!
0*
05
09
0=
#2315000000
1!
1*
15
19
1=
#2320000000
0!
0*
05
09
0=
#2325000000
1!
1*
15
19
1=
#2330000000
0!
0*
05
09
0=
#2335000000
1!
1*
15
19
1=
#2340000000
0!
0*
05
09
0=
#2345000000
1!
1*
15
19
1=
#2350000000
0!
0*
05
09
0=
#2355000000
1!
1*
15
19
1=
#2360000000
0!
0*
05
09
0=
#2365000000
1!
1*
15
19
1=
#2370000000
0!
0*
05
09
0=
#2375000000
1!
1*
15
19
1=
#2380000000
0!
0*
05
09
0=
#2385000000
1!
1*
15
19
1=
#2390000000
0!
0*
05
09
0=
#2395000000
1!
1$
1*
15
18
19
1=
1?
#2400000000
0!
0*
05
09
0=
#2405000000
1!
0$
1*
15
08
19
1=
0?
#2410000000
0!
0*
05
09
0=
#2415000000
1!
1*
15
19
1=
#2420000000
0!
0*
05
09
0=
#2425000000
1!
1*
15
19
1=
#2430000000
0!
0*
05
09
0=
#2435000000
1!
1*
15
19
1=
#2440000000
0!
0*
05
09
0=
#2445000000
1!
1*
15
19
1=
#2450000000
0!
0*
05
09
0=
#2455000000
1!
1*
15
19
1=
#2460000000
0!
0*
05
09
0=
#2465000000
1!
1*
15
19
1=
#2470000000
0!
0*
05
09
0=
#2475000000
1!
1*
15
19
1=
#2480000000
0!
0*
05
09
0=
#2485000000
1!
1*
15
19
1=
#2490000000
0!
0*
05
09
0=
#2495000000
1!
1$
1*
15
18
19
1=
1?
#2500000000
0!
0*
05
09
0=
#2505000000
1!
0$
1*
15
08
19
1=
0?
#2510000000
0!
0*
05
09
0=
#2515000000
1!
1*
15
19
1=
#2520000000
0!
0*
05
09
0=
#2525000000
1!
1*
15
19
1=
#2530000000
0!
0*
05
09
0=
#2535000000
1!
1*
15
19
1=
#2540000000
0!
0*
05
09
0=
#2545000000
1!
1*
15
19
1=
#2550000000
0!
0*
05
09
0=
